django_pds/__init__.py
django_pds/apps.py
django_pds/conf.py
django_pds/middlewares.py
django_pds/serializers.py
django_pds/core/__init__.py
django_pds/core/errors.py
django_pds/core/querysets.py
django_pds/core/settings.py
django_pds/core/utils.py
django_pds/core/base/__init__.py
django_pds/core/base/document.py
django_pds/core/helper/__init__.py
django_pds/core/helper/xstr.py
django_pds/core/managers/__init__.py
django_pds/core/managers/delete.py
django_pds/core/managers/entity.py
django_pds/core/managers/insert.py
django_pds/core/managers/kwargs.py
django_pds/core/managers/manager.py
django_pds/core/managers/read.py
django_pds/core/managers/required.py
django_pds/core/managers/update.py
django_pds/core/managers/userreadabledata.py
django_pds/core/managers/userrolemaps.py
django_pds/core/pds/__init__.py
django_pds/core/pds/generic/__init__.py
django_pds/core/pds/generic/delete.py
django_pds/core/pds/generic/read.py
django_pds/core/pds/generic/update.py
django_pds/core/pds/generic/upsert.py
django_pds/core/pds/generic/write.py
django_pds/core/pds/parser/__init__.py
django_pds/core/pds/parser/query.py
django_pds/core/pds/parser/terms.py
django_pds/core/rest/__init__.py
django_pds/core/rest/decorators.py
django_pds/core/rest/exceptions.py
django_pds/core/rest/response.py
django_pds/core/rest/views.py
django_pds/models/__init__.py
django_pds/models/entity.py
django_pds/models/entitydefaultpermissionsettings.py
django_pds/models/userreadabledata.py
django_pds/models/userrolemaps.py
django_pds-0.0.6.dist-info/LICENSE
django_pds-0.0.6.dist-info/METADATA
django_pds-0.0.6.dist-info/WHEEL
django_pds-0.0.6.dist-info/top_level.txt
django_pds-0.0.6.dist-info/RECORD
