Metadata-Version: 2.1
Name: django-pds
Version: 0.0.6
Summary: Django Platform Data Service
Home-page: https://github.com/knroy/django-pds
Author: Komol Nath Roy
Author-email: rax.komol@gmail.com   
License: MIT
Platform: UNKNOWN
Classifier: License :: OSI Approved :: MIT License
Classifier: Programming Language :: Python
Classifier: Programming Language :: Python :: 3
Classifier: Programming Language :: Python :: 3.6
Classifier: Programming Language :: Python :: Implementation :: CPython
Classifier: Programming Language :: Python :: Implementation :: PyPy
Classifier: Operating System :: OS Independent
Requires-Python: >=3.6.0
Requires-Dist: django (>=3.0.6)
Requires-Dist: djangorestframework (>=3.11.0)
Requires-Dist: django-rest-framework-mongoengine (>=3.4.1)
Requires-Dist: mongoengine (>=0.20.0)
Requires-Dist: python-dateutil (>=2.8.1)
Requires-Dist: psycopg2-binary (>=2.8.5)
Requires-Dist: django-cors-headers (>=3.2.1)
Requires-Dist: PyJWT (>=1.7.1)
